{
  "queue": [
    {
      "url": "https://www.instagram.com/ahfood12/reel/DP1GFN-iQLv/",
      "username": "ahfood12",
      "notes": "Auto-added from reels_source.txt",
      "added_at": "2026-06-20T12:23:12.508440+00:00"
    }
  ],
  "processed": [
    {
      "url": "https://www.instagram.com/the_cinnamom/reel/DRtmGtMj_Gd/",
      "username": "the_cinnamom",
      "status": "in_progress",
      "started_at": "2026-06-20T11:52:18.677166+00:00"
    }
  ],
  "metadata": {
    "total_queued": 1,
    "total_processed": 0,
    "last_run": "2026-06-20T12:23:12.508520+00:00",
    "next_scheduled": null
  }
}